LICENSE
README.md
SNAPy/__init__.py
SNAPy/calcs.py
SNAPy/main.py
SNAPy/prcs_geom.py
SNAPy/prcs_grph.py
SNAPy/prcs_sna.py
SNAPy/routines.py
SNAPy/utils.py
SNAPy/SGACy/geom.cp311-win_amd64.pyd
SNAPy/SGACy/geom.cp312-win_amd64.pyd
SNAPy/SGACy/geom.cpp
SNAPy/SGACy/geom.cpython-312-darwin.so
SNAPy/SGACy/geom.pyx
SNAPy/SGACy/graph.cp311-win_amd64.pyd
SNAPy/SGACy/graph.cp312-win_amd64.pyd
SNAPy/SGACy/graph.cpp
SNAPy/SGACy/graph.cpython-312-darwin.so
SNAPy/SGACy/graph.pyx
SNAPy/SGACy/setup.py
snapy_toolbox.egg-info/PKG-INFO
snapy_toolbox.egg-info/SOURCES.txt
snapy_toolbox.egg-info/dependency_links.txt
snapy_toolbox.egg-info/requires.txt
snapy_toolbox.egg-info/top_level.txt
snapy_toolbox-0.2.14.dist-info/LICENSE
snapy_toolbox-0.2.14.dist-info/METADATA
snapy_toolbox-0.2.14.dist-info/WHEEL
snapy_toolbox-0.2.14.dist-info/top_level.txt
snapy_toolbox-0.2.14.dist-info/RECORD
